neoassistant/__init__.py
neoassistant/__main__.py
neoassistant/argument_parser.py
neoassistant/assistant.py
neoassistant/commands.py
neoassistant/contact_book.py
neoassistant/errors.py
neoassistant/fields.py
neoassistant/note_book.py
neoassistant/rich_formatter.py
neoassistant-0.1.4.dist-info/LICENSE
neoassistant-0.1.4.dist-info/METADATA
neoassistant-0.1.4.dist-info/WHEEL
neoassistant-0.1.4.dist-info/entry_points.txt
neoassistant-0.1.4.dist-info/top_level.txt
neoassistant-0.1.4.dist-info/RECORD
