Metadata-Version: 2.1
Name: neoassistant
Version: 0.1.4
Summary: A CLI application that helps to manage contacts and notes.
Author-email: Illja <a4grtu@gmail.com>, Olha Levchenko <olgakazakovskaya@ukr.net>, Vladyslav Mazur <vladopermoz@gmail.com>, Zakir Nuriiev <kazamov@gmail.com>
License: MIT License
Project-URL: Homepage, https://github.com/kazamov/goitneo-python-final-project-group-11/
Keywords: assistant,contacts,notes
Requires-Python: >=3.10
License-File: LICENSE
Requires-Dist: rich
Provides-Extra: dev
Requires-Dist: black ; extra == 'dev'
Requires-Dist: pylint ; extra == 'dev'
Requires-Dist: isort ; extra == 'dev'
Requires-Dist: pytest ; extra == 'dev'
Requires-Dist: build ; extra == 'dev'
Requires-Dist: twine ; extra == 'dev'
